{
	"name": "Advanced JavaScript Projects",
	"order": 7,
	"time": "70 hours",
	"helpRoom": "Help",
	"challenges": [
    {
      "id": "f7ca76b015acb7ce93ec576c",
      "title": "** Commit to not solve other students problems",
      "description": [
        [
          "",
          "",
          "Computer programming requires excellent problem solving skills.<br><br>Working through problems with the help of documentation is a daily activity for all programmers.",
          ""
        ],
        [
          "",
          "",
          "When students give help it should only be to point out where in the documentation, books or other materials where they can learn about a concept.",
          ""
        ],
        [
          "",
          "",
          "Students should never give away a solution to a problem or share code that completes a problem.",
          ""
        ],
        [
          "",
          "",
          "If a student is still unable to solve a problem, please, refer them to the tutor.",
          ""
        ],
        [
          "",
          "",
          "If you and the other student(s) have finished and passed off the project or challenge feel free to discuss, share techniques and source code.",
          ""
        ],
        [
          "",
          "",
          "However, <strong>please</strong> do not discuss within earshot of other students that have not passed off to that point.",
          ""
        ],
        [
          "",
          "",
          "By clicking below you commit to <strong>not</strong> solve other students problems, share code or give away answers.",
          "#"
        ]
      ],
      "releasedOn": "May 10, 2018",
      "challengeSeed": [],
      "tests": [],
      "type": "Waypoint",
      "challengeType": 7,
      "isRequired": true
    },
		{
			"id": "49aaa9901419a1dace811077",
			"title": "Virtual Life App with ES6 Modules",
			"description": [
				"Build the app as defined in the project definition.",
				"<a href='https://redrockcode.com/educationMaterials/workbenchProjects/phase-i/virtual-life-04-es6-modules/virtual-life-04-es6-modules.html' target='_blank' class='btn btn-primary'>Click here</a> to see the project definition.",
				"<a href='https://redrockcode.com/educationMaterials/workbenchProjects/phase-i/virtual-life-04-es6-modules/virtual-life-04-es6-modules.png' target='_blank'><img src='https://redrockcode.com/educationMaterials/workbenchProjects/phase-i/virtual-life-04-es6-modules/virtual-life-04-es6-modules.png'></a>",
				"Remember to use the Research-Ask method if you get stuck."
			],
			"releasedOn": "January 8, 2019",
			"challengeSeed": [
				"qHu6mXf"
			],
			"tests": [],
			"type": "zipline",
			"isRequired": true,
			"challengeType": 3
		},
		{
			"id": "48e3d7201419772eb9859df1",
			"title": "Virtual Life App with ES6 Modules Source Code Review",
			"description": [
				[
					"",
					"",
					"Confirm that you have that you have completed and submitted the Virtual Life App with ES6 Modules.",
					"#"
				],
				[
					"",
					"",
					"Please review the professional source code and compare it to your own.<br><br><a href='https://redrockcode.com/educationMaterials/workbenchProjects/review/virtual-life-04-es6-modules-48e3d7201419772eb9859df1/' target='_blank' class='btn btn-primary'>Click here</a> to view the professional source code.",
					""
				],
				[
					"",
					"",
					"Confirm you have reviewed the professional source code.",
					"#"
				]
			],
			"releasedOn": "January 8, 2019",
			"challengeSeed": [],
			"tests": [],
			"type": "Waypoint",
			"isRequired": true,
			"challengeType": 7,
			"prerequisite": "49aaa9901419a1dace811077"
		},
		{
			"id": "9dbbaaf0144d3f38b286fad2",
			"title": "Virtual Life App with Inheritance",
			"description": [
				"Build the app as defined in the project definition.",
				"<a href='https://redrockcode.com/educationMaterials/workbenchProjects/phase-i/virtual-life-05-inheritance/virtual-life-05-inheritance.html' target='_blank' class='btn btn-primary'>Click here</a> to see the project definition.",
				"<a href='https://redrockcode.com/educationMaterials/workbenchProjects/phase-i/virtual-life-05-inheritance/virtual-life-05-inheritance.png' target='_blank'><img src='https://redrockcode.com/educationMaterials/workbenchProjects/phase-i/virtual-life-05-inheritance/virtual-life-05-inheritance.png'></a>",
				"Remember to use the Research-Ask method if you get stuck."
			],
			"releasedOn": "January 8, 2019",
			"challengeSeed": [
				"68yNN2h"
			],
			"tests": [],
			"type": "zipline",
			"isRequired": true,
			"challengeType": 3
		},
		{
			"id": "9e5f3df0144dcf91eb372a55",
			"title": "Virtual Life App with Inheritance Source Code Review",
			"description": [
				[
					"",
					"",
					"Confirm that you have that you have completed and submitted the Virtual Life App with Inheritance.",
					"#"
				],
				[
					"",
					"",
					"Please review the professional source code and compare it to your own.<br><br><a href='https://redrockcode.com/educationMaterials/workbenchProjects/review/virtual-life-05-inheritance-9e5f3df0144dcf91eb372a55/' target='_blank' class='btn btn-primary'>Click here</a> to view the professional source code.",
					""
				],
				[
					"",
					"",
					"Confirm you have reviewed the professional source code.",
					"#"
				]
			],
			"releasedOn": "January 8, 2019",
			"challengeSeed": [],
			"tests": [],
			"type": "Waypoint",
			"isRequired": true,
			"challengeType": 7,
			"prerequisite": "9dbbaaf0144d3f38b286fad2"
		},
		{
			"id": "7967a460145235cb14329ba6",
			"title": "Virtual Life App with Carnivore",
			"description": [
				"Build the app as defined in the project definition.",
				"<a href='https://redrockcode.com/educationMaterials/workbenchProjects/phase-i/virtual-life-06-carnivore/virtual-life-06-carnivore.html' target='_blank' class='btn btn-primary'>Click here</a> to see the project definition.",
				"<a href='https://redrockcode.com/educationMaterials/workbenchProjects/phase-i/virtual-life-06-carnivore/virtual-life-06-carnivore.png' target='_blank'><img src='https://redrockcode.com/educationMaterials/workbenchProjects/phase-i/virtual-life-06-carnivore/virtual-life-06-carnivore.png'></a>",
				"Remember to use the Research-Ask method if you get stuck."
			],
			"releasedOn": "January 8, 2019",
			"challengeSeed": [
				"3uYZjoh"
			],
			"tests": [],
			"type": "zipline",
			"isRequired": true,
			"challengeType": 3
		},
		{
			"id": "7a00d7201452f17f153f9f7f",
			"title": "Virtual Life App with Carnivore Source Code Review",
			"description": [
				[
					"",
					"",
					"Confirm that you have that you have completed and submitted the Virtual Life App with Carnivore.",
					"#"
				],
				[
					"",
					"",
					"Please review the professional source code and compare it to your own.<br><br><a href='https://redrockcode.com/educationMaterials/workbenchProjects/review/virtual-life-06-carnivore-7a00d7201452f17f153f9f7f/' target='_blank' class='btn btn-primary'>Click here</a> to view the professional source code.",
					""
				],
				[
					"",
					"",
					"Confirm you have reviewed the professional source code.",
					"#"
				]
			],
			"releasedOn": "January 8, 2019",
			"challengeSeed": [],
			"tests": [],
			"type": "Waypoint",
			"isRequired": true,
			"challengeType": 7,
			"prerequisite": "7967a460145235cb14329ba6"
		},
		{
			"id": "4ceff2f015ade7754d1e5c40",
			"title": "Virtual Life App with Animation",
			"description": [
				"Build the app as defined in the project definition.",
				"<a href='https://redrockcode.com/educationMaterials/workbenchProjects/phase-i/virtual-life-07-animate-text/virtual-life-07-animate-text.html' target='_blank' class='btn btn-primary'>Click here</a> to see the project definition.",
				"<a href='https://redrockcode.com/educationMaterials/workbenchProjects/phase-i/virtual-life-07-animate-text/virtual-life-07-animate-text.png' target='_blank'><img src='https://redrockcode.com/educationMaterials/workbenchProjects/phase-i/virtual-life-07-animate-text/virtual-life-07-animate-text.png' style='width:500px'></a>",
				"Remember to use the Research-Ask method if you get stuck."
			],
			"releasedOn": "January 11, 2019",
			"challengeSeed": [
				"5lkI2VA"
			],
			"tests": [],
			"type": "zipline",
			"isRequired": true,
			"challengeType": 3
		},
		{
			"id": "4d5fcbc015ad45d58190084f",
			"title": "Virtual Life App with Animation Source Code Review",
			"description": [
				[
					"",
					"",
					"Confirm that you have that you have completed and submitted the Virtual Life App with Animation.",
					"#"
				],
				[
					"",
					"",
					"Please review the professional source code and compare it to your own.<br><br><a href='https://redrockcode.com/educationMaterials/workbenchProjects/review/virtual-life-07-animate-text-4d5fcbc015ad45d58190084f/' target='_blank' class='btn btn-primary'>Click here</a> to view the professional source code.",
					""
				],
				[
					"",
					"",
					"Confirm you have reviewed the professional source code.",
					"#"
				]
			],
			"releasedOn": "January 11, 2019",
			"challengeSeed": [],
			"tests": [],
			"type": "Waypoint",
			"isRequired": true,
			"challengeType": 7,
			"prerequisite": "4ceff2f015ade7754d1e5c40"
		},
		{
			"id": "b76579a015dc81c4130c6dba",
			"title": "Virtual Life App with Animation and Styling",
			"description": [
				"Build the app as defined in the project definition.",
				"<a href='https://redrockcode.com/educationMaterials/workbenchProjects/phase-i/virtual-life-08-animate-icons/virtual-life-08-animate-icons.html' target='_blank' class='btn btn-primary'>Click here</a> to see the project definition.",
				"<a href='https://redrockcode.com/educationMaterials/workbenchProjects/phase-i/virtual-life-08-animate-icons/virtual-life-08-animate-icons.png' target='_blank'><img src='https://redrockcode.com/educationMaterials/workbenchProjects/phase-i/virtual-life-08-animate-icons/virtual-life-08-animate-icons.png' style='width:500px'></a>",
				"<a href='https://redrockcode.com/educationMaterials/workbenchProjects/phase-i/virtual-life-08-animate-icons/virtual-life-08-animate-icons-alt.png' target='_blank'><img src='https://redrockcode.com/educationMaterials/workbenchProjects/phase-i/virtual-life-08-animate-icons/virtual-life-08-animate-icons-alt.png' style='width:500px'></a>",
				"Remember to use the Research-Ask method if you get stuck."
			],
			"releasedOn": "January 11, 2019",
			"challengeSeed": [
				"7UMSzOr"
			],
			"tests": [],
			"type": "zipline",
			"isRequired": true,
			"challengeType": 3
		},
		{
			"id": "b8359ae015dc9d5d3f60a85a",
			"title": "Virtual Life App with Animation and Styling Source Code Review",
			"description": [
				[
					"",
					"",
					"Confirm that you have that you have completed and submitted the Virtual Life App with Animation and Styling.",
					"#"
				],
				[
					"",
					"",
					"Please review the professional source code and compare it to your own.<br><br><a href='https://redrockcode.com/educationMaterials/workbenchProjects/review/virtual-life-08-animate-icons-b8359ae015dc9d5d3f60a85a/' target='_blank' class='btn btn-primary'>Click here</a> to view the professional source code.",
					""
				],
				[
					"",
					"",
					"Confirm you have reviewed the professional source code.",
					"#"
				]
			],
			"releasedOn": "January 11, 2019",
			"challengeSeed": [],
			"tests": [],
			"type": "Waypoint",
			"isRequired": true,
			"challengeType": 7,
			"prerequisite": "b76579a015dc81c4130c6dba"
		}
	]
  }
  